mainwrapper/__init__.py
mainwrapper/__main__.py
mainwrapper/version.py
mainwrapper/tests/__init__.py
mainwrapper/tests/test_mainwrapper.py
main_wrapper-0.1.1.dist-info/LICENSE
main_wrapper-0.1.1.dist-info/METADATA
main_wrapper-0.1.1.dist-info/WHEEL
main_wrapper-0.1.1.dist-info/entry_points.txt
main_wrapper-0.1.1.dist-info/top_level.txt
main_wrapper-0.1.1.dist-info/RECORD
