Metadata-Version: 2.1
Name: main-wrapper
Version: 0.1.1
Summary: Set up global environment and run another script within, ala pdb, profile, etc..
Home-page: https://github.com/rpatterson/python-main-wrapper
Author: Ross Patterson
Author-email: me@rpatterson.net
License: MIT
Platform: UNKNOWN
Classifier: Development Status :: 4 - Beta
Classifier: Environment :: Console
Classifier: Intended Audience :: Developers
Classifier: Intended Audience :: System Administrators
Classifier: License :: OSI Approved :: MIT License
Classifier: Natural Language :: English
Classifier: Operating System :: OS Independent
Classifier: Programming Language :: Python :: 3
Classifier: Topic :: Utilities
Requires-Python: >=2.7
License-File: LICENSE
Requires-Dist: six
Requires-Dist: pathlib2 ; python_version < "3"
Provides-Extra: dev
Requires-Dist: six ; extra == 'dev'
Requires-Dist: pytest ; extra == 'dev'
Requires-Dist: pre-commit ; extra == 'dev'
Requires-Dist: coverage ; extra == 'dev'
Requires-Dist: flake8 ; extra == 'dev'
Requires-Dist: autoflake ; extra == 'dev'
Requires-Dist: autopep8 ; extra == 'dev'
Requires-Dist: rstcheck ; extra == 'dev'
Requires-Dist: contextlib2 ; (python_version < "3") and extra == 'dev'
Requires-Dist: flake8-black ; (python_version >= "3") and extra == 'dev'
